aliyunsdklive/__init__.py
aliyunsdklive/endpoint.py
aliyunsdklive/request/__init__.py
aliyunsdklive/request/v20161101/AddCasterComponentRequest.py
aliyunsdklive/request/v20161101/AddCasterEpisodeGroupContentRequest.py
aliyunsdklive/request/v20161101/AddCasterEpisodeGroupRequest.py
aliyunsdklive/request/v20161101/AddCasterEpisodeRequest.py
aliyunsdklive/request/v20161101/AddCasterLayoutRequest.py
aliyunsdklive/request/v20161101/AddCasterProgramRequest.py
aliyunsdklive/request/v20161101/AddCasterVideoResourceRequest.py
aliyunsdklive/request/v20161101/AddCustomLiveStreamTranscodeRequest.py
aliyunsdklive/request/v20161101/AddLiveAIProduceRulesRequest.py
aliyunsdklive/request/v20161101/AddLiveAISubtitleRequest.py
aliyunsdklive/request/v20161101/AddLiveAppRecordConfigRequest.py
aliyunsdklive/request/v20161101/AddLiveAppSnapshotConfigRequest.py
aliyunsdklive/request/v20161101/AddLiveAudioAuditConfigRequest.py
aliyunsdklive/request/v20161101/AddLiveAudioAuditNotifyConfigRequest.py
aliyunsdklive/request/v20161101/AddLiveCenterTransferRequest.py
aliyunsdklive/request/v20161101/AddLiveDetectNotifyConfigRequest.py
aliyunsdklive/request/v20161101/AddLiveDomainMappingRequest.py
aliyunsdklive/request/v20161101/AddLiveDomainPlayMappingRequest.py
aliyunsdklive/request/v20161101/AddLiveDomainRequest.py
aliyunsdklive/request/v20161101/AddLiveMessageGroupBandRequest.py
aliyunsdklive/request/v20161101/AddLivePackageConfigRequest.py
aliyunsdklive/request/v20161101/AddLivePullStreamInfoConfigRequest.py
aliyunsdklive/request/v20161101/AddLiveRecordNotifyConfigRequest.py
aliyunsdklive/request/v20161101/AddLiveRecordVodConfigRequest.py
aliyunsdklive/request/v20161101/AddLiveSnapshotDetectPornConfigRequest.py
aliyunsdklive/request/v20161101/AddLiveSnapshotNotifyConfigRequest.py
aliyunsdklive/request/v20161101/AddLiveStreamMergeRequest.py
aliyunsdklive/request/v20161101/AddLiveStreamTranscodeRequest.py
aliyunsdklive/request/v20161101/AddLiveStreamWatermarkRequest.py
aliyun_python_sdk_live-3.9.73.dist-info/LICENSE
aliyun_python_sdk_live-3.9.73.dist-info/METADATA
aliyun_python_sdk_live-3.9.73.dist-info/WHEEL
aliyun_python_sdk_live-3.9.73.dist-info/top_level.txt
aliyun_python_sdk_live-3.9.73.dist-info/RECORD
